satta_king_uk_bazar/__init__.py
satta_king_uk_bazar/app.py
satta_king_uk_bazar/main.py
satta_king_uk_bazar/data/games.json
satta_king_uk_bazar/data/monthly_results.json
satta_king_uk_bazar/static/robots.txt
satta_king_uk_bazar/static/css/style.css
satta_king_uk_bazar/static/js/main.js
satta_king_uk_bazar/templates/base.html
satta_king_uk_bazar/templates/game_chart.html
satta_king_uk_bazar/templates/index.html
satta_king_uk_bazar/templates/monthly_chart.html
satta_king_uk_bazar_webapp-1.0.0.dist-info/licenses/LICENSE
satta_king_uk_bazar_webapp-1.0.0.dist-info/METADATA
satta_king_uk_bazar_webapp-1.0.0.dist-info/WHEEL
satta_king_uk_bazar_webapp-1.0.0.dist-info/entry_points.txt
satta_king_uk_bazar_webapp-1.0.0.dist-info/top_level.txt
satta_king_uk_bazar_webapp-1.0.0.dist-info/RECORD
