Metadata-Version: 2.4
Name: satta-king-uk-bazar-webapp
Version: 1.0.0
Summary: A Flask-based gaming results website with live updates and SEO optimization
Author-email: Developer <developer@example.com>
License: MIT
Project-URL: Homepage, https://github.com/username/satta-king-uk-bazar
Project-URL: Repository, https://github.com/username/satta-king-uk-bazar.git
Project-URL: Documentation, https://github.com/username/satta-king-uk-bazar#readme
Project-URL: Bug Tracker, https://github.com/username/satta-king-uk-bazar/issues
Keywords: flask,web,gaming,results,seo,responsive
Classifier: Development Status :: 5 - Production/Stable
Classifier: Environment :: Web Environment
Classifier: Framework :: Flask
Classifier: Intended Audience :: Developers
Classifier: License :: OSI Approved :: MIT License
Classifier: Operating System :: OS Independent
Classifier: Programming Language :: Python :: 3
Classifier: Programming Language :: Python :: 3.8
Classifier: Programming Language :: Python :: 3.9
Classifier: Programming Language :: Python :: 3.10
Classifier: Programming Language :: Python :: 3.11
Classifier: Programming Language :: Python :: 3.12
Classifier: Topic :: Internet :: WWW/HTTP :: Dynamic Content
Classifier: Topic :: Internet :: WWW/HTTP :: WSGI :: Application
Classifier: Topic :: Software Development :: Libraries :: Python Modules
Requires-Python: >=3.8
License-File: LICENSE
Requires-Dist: flask>=2.0.0
Requires-Dist: gunicorn>=20.0.0
Provides-Extra: dev
Requires-Dist: pytest>=6.0; extra == "dev"
Requires-Dist: pytest-flask>=1.0; extra == "dev"
Requires-Dist: black>=22.0; extra == "dev"
Requires-Dist: flake8>=4.0; extra == "dev"
Dynamic: license-file
